django_wrapper_tag-0.1.17.dist-info/DESCRIPTION.rst
django_wrapper_tag-0.1.17.dist-info/METADATA
django_wrapper_tag-0.1.17.dist-info/metadata.json
django_wrapper_tag-0.1.17.dist-info/pbr.json
django_wrapper_tag-0.1.17.dist-info/RECORD
django_wrapper_tag-0.1.17.dist-info/top_level.txt
django_wrapper_tag-0.1.17.dist-info/WHEEL
wrapper_tag/__init__.py
wrapper_tag/apps.py
wrapper_tag/arguments.py
wrapper_tag/docgen.py
wrapper_tag/mixins.py
wrapper_tag/models.py
wrapper_tag/rendered.py
wrapper_tag/tag.py
wrapper_tag/urls.py
wrapper_tag/utils.py
wrapper_tag/validators.py
wrapper_tag/views.py
wrapper_tag/management/__init__.py
wrapper_tag/management/commands/__init__.py
wrapper_tag/management/commands/tagdoc.py
wrapper_tag/static/css/wrapper_tag.css
wrapper_tag/static/js/wrapper_tag.js
wrapper_tag/templates/wrapper_tag/base.html
wrapper_tag/templatetags/__init__.py
wrapper_tag/templatetags/wrapper_tag_test_tags.py
