Metadata-Version: 1.1
Name: django-wrapper-tag
Version: 0.1.17
Summary: Wrapping template tag for django
Home-page: https://github.com/phonkee/django-wrapper-tag
Author: Peter Vrba
Author-email: phonkee@phonkee.eu
License: MIT
Keywords: django-wrapper-tag
Platform: UNKNOWN
Classifier: Development Status :: 3 - Alpha
Classifier: Framework :: Django
Classifier: Framework :: Django :: 1.10
Classifier: Intended Audience :: Developers
Classifier: License :: OSI Approved :: BSD License
Classifier: Natural Language :: English
Classifier: Programming Language :: Python :: 2
Classifier: Programming Language :: Python :: 2.7
Classifier: Programming Language :: Python :: 3
Classifier: Programming Language :: Python :: 3.4
Classifier: Programming Language :: Python :: 3.5
